main.py
dropbox_paper_export-0.1.0.dist-info/licenses/LICENSE
dropbox_paper_export-0.1.0.dist-info/METADATA
dropbox_paper_export-0.1.0.dist-info/WHEEL
dropbox_paper_export-0.1.0.dist-info/entry_points.txt
dropbox_paper_export-0.1.0.dist-info/top_level.txt
dropbox_paper_export-0.1.0.dist-info/RECORD
