Metadata-Version: 2.4
Name: dropbox-paper-export
Version: 0.1.0
Summary: Export Dropbox Paper documents to markdown
License-Expression: MIT
Keywords: dropbox,paper,markdown,export,backup
Classifier: Programming Language :: Python :: 3.12
Requires-Python: >=3.12
License-File: LICENSE
Requires-Dist: dropbox==12.0.2
Requires-Dist: requests==2.32.5
Requires-Dist: ruff==0.14.8
Requires-Dist: tqdm==4.67.1
Dynamic: license-file
